xlutil/__init__.py
xlutil/constants.py
xlutil/core/__init__.py
xlutil/core/utils.py
xlutil-0.1.3.dist-info/LICENSE
xlutil-0.1.3.dist-info/METADATA
xlutil-0.1.3.dist-info/WHEEL
xlutil-0.1.3.dist-info/RECORD
